<?xml version="1.0" encoding="utf-8" standalone="no"?>
<extension group="system" method="upgrade" type="plugin" version="30">
	<name>plg_fabrik_system</name>
	<author>Fabrikar.com</author>
	<creationDate>${createdate}</creationDate>
	<copyright>(C) 2005-${year} fabrikar.com</copyright>
	<license>http://www.gnu.org/licenses/gpl-2.0.html GNU/GPL</license>
	<authorEmail>rob@pollen-8.co.uk</authorEmail>
	<authorUrl>www.pollen-8.co.uk</authorUrl>
	<version>3.1b</version>
	<description>PLG_FABRIK_SYSTEM_DESCRIPTION</description>
	<files>
		<filename plugin="fabrik">fabrik.php</filename>
		<filename>defines.php</filename>
		<folder>language</folder>
	</files>
	<config>
	</config>
</extension>
