<?xml version="1.0" encoding="UTF-8" standalone="no"?>
<form>
	<fields name="params">
		<fieldset name="plg-form-sms">
			<field description="PLG_FORM_SMS_GATEWAY_DESC" directory="plugins/fabrik_form/sms/gateway" hide_default="true" hide_none="true" label="PLG_FORM_SMS_GATEWAY_LABEL" name="sms-gateway" type="filelist"/>
				
			<field default="" label="PLG_FORM_SMS_USERNAME_LABEL" name="sms-username" size="30" type="text"/>
				
			<field default="" label="PLG_FORM_SMS_PASSWORD_LABEL" name="sms-password" size="30" type="text"/>
				
			<field default="" description="PLG_FORM_SMS_MOBILE_DESC" label="PLG_FORM_SMS_MOBILE_LABEL" name="sms-to" size="30" type="text"/>
				
			<field default="" description="SENDERS_MOBILE_NUM_DESC" label="PLG_FORM_SMS_SENDERS_MOBILE_NUM_LABEL" name="sms-from" size="30" type="text"/>
		</fieldset>
	</fields>
</form>
